rtp/__init__.py
rtp/csrcList.py
rtp/errors.py
rtp/extension.py
rtp/payloadType.py
rtp/py.typed
rtp/rtp.py
rtp-0.0.3.dist-info/LICENSE
rtp-0.0.3.dist-info/METADATA
rtp-0.0.3.dist-info/WHEEL
rtp-0.0.3.dist-info/top_level.txt
rtp-0.0.3.dist-info/RECORD
