Metadata-Version: 2.1
Name: rtp
Version: 0.0.3
Summary: A library for decoding/encoding rtp packets
Home-page: https://github.com/bbc/rd-apmm-python-lib-rtp
Author: BBC R&D
Author-email: cloudfit-opensource@rd.bbc.co.uk
License: apache-2.0
Platform: UNKNOWN
License-File: LICENSE
